{
  "version": 1,
  "dependencies": [
    {
      "source": {
        "git": {
          "remote": "https://github.com/grafana/jsonnet-libs.git",
          "subdir": "ksonnet-util"
        }
      },
      "version": "9927be87af4be9ff6b009e4503868b1b5493011b",
      "sum": "fFVlCoa/N0qiqTbDhZAEdRm2Vv76Z9Clxp3/haJ+PyA="
    },
    {
      "source": {
        "git": {
          "remote": "https://github.com/grafana/jsonnet-libs.git",
          "subdir": "memcached"
        }
      },
      "version": "9927be87af4be9ff6b009e4503868b1b5493011b",
      "sum": "dTOeEux3t9bYSqP2L/uCuLo/wUDpCKH4w+4OD9fePUk="
    },
    {
      "source": {
        "git": {
          "remote": "https://github.com/ksonnet/ksonnet-lib.git",
          "subdir": "ksonnet.beta.4"
        }
      },
      "version": "0d2f82676817bbf9e4acf6495b2090205f323b9f",
      "sum": "ur22hPQq0JAPBxm8hNMcwjumj4MkozDwOKiGZvVMYh4="
    },
    {
      "source": {
        "local": {
          "directory": "../../jsonnet/microservices"
        }
      },
      "version": ""
    }
  ],
  "legacyImports": false
}
